ElijeTuPok/__init__.py
ElijeTuPok/pokemon.csv
ElijeTuPok/random_pokemon.py
Impctunder/__init__.py
Impctunder/pokemon.csv
Impctunder/random_pokemon.py
Snorlax/__init__.py
Snorlax/pokemon.csv
Snorlax/random_pokemon.py
YoteelijSnorlax/__init__.py
YoteelijSnorlax/pokemon.csv
YoteelijSnorlax/random_pokemon.py
Impctunder-1.0.3.dist-info/METADATA
Impctunder-1.0.3.dist-info/WHEEL
Impctunder-1.0.3.dist-info/top_level.txt
Impctunder-1.0.3.dist-info/RECORD
