Metadata-Version: 2.1
Name: Impctunder
Version: 1.0.3
Summary: Una Biblioteca que contiene la clase Random_pokemon para mostranos poquemones locos
Author: Missael Angel Cardenas
Author-email: missaelanggel@gmail.com
Requires-Dist: pandas
Requires-Dist: pkg-resources
Requires-Dist: setuptools
Requires-Dist: twine
Requires-Dist: wheel
